mvvm_lib/__init__.py
mvvm_lib/bindings_map.py
mvvm_lib/interface.py
mvvm_lib/panel_binding/__init__.py
mvvm_lib/panel_binding/binding.py
mvvm_lib/pydantic_utils.py
mvvm_lib/pyqt_binding/__init__.py
mvvm_lib/pyqt_binding/binding.py
mvvm_lib/trame_binding/__init__.py
mvvm_lib/trame_binding/binding.py
mvvm_lib/utils.py
mvvm_lib-0.5.0.dist-info/LICENSE
mvvm_lib-0.5.0.dist-info/METADATA
mvvm_lib-0.5.0.dist-info/WHEEL
mvvm_lib-0.5.0.dist-info/entry_points.txt
mvvm_lib-0.5.0.dist-info/RECORD
