Metadata-Version: 2.1
Name: mvvm-lib
Version: 0.5.0
Summary: A Python Package for Model-View-ViewModel pattern
License: MIT
Keywords: MVVM,python
Author: Yakubov, Sergey
Author-email: yakubovs@ornl.gov
Requires-Python: >=3.10,<4.0
Classifier: License :: OSI Approved :: MIT License
Classifier: Programming Language :: Python :: 3
Classifier: Programming Language :: Python :: 3.10
Classifier: Programming Language :: Python :: 3.11
Classifier: Programming Language :: Python :: 3.12
Classifier: Programming Language :: Python :: 3.13
Provides-Extra: panel
Provides-Extra: pyqt5
Provides-Extra: pyqt6
Requires-Dist: panel (>=1.4.4,<2.0.0) ; extra == "panel"
Requires-Dist: pyqt5 (>=5.15.11,<6.0.0) ; extra == "pyqt5"
Requires-Dist: pyqt6 (>=6.7.0,<7.0.0) ; extra == "pyqt6"
Requires-Dist: trame (>=3.6.3,<4.0.0)
